uniqfunc/__init__.py
uniqfunc/cli.py
uniqfunc/fingerprint.py
uniqfunc/formatters.py
uniqfunc/git_files.py
uniqfunc/logging_config.py
uniqfunc/model.py
uniqfunc/parser.py
uniqfunc/similarity.py
uniqfunc/similarity_ast.py
uniqfunc/similarity_name_signature.py
uniqfunc-0.1.3.dist-info/METADATA
uniqfunc-0.1.3.dist-info/WHEEL
uniqfunc-0.1.3.dist-info/entry_points.txt
uniqfunc-0.1.3.dist-info/licenses/LICENSE
uniqfunc-0.1.3.dist-info/RECORD
