Metadata-Version: 2.4
Name: uniqfunc
Version: 0.1.3
Summary: Git-aware checker for globally unique Python function names + reuse suggestions for AI agents
Author-email: Alex Dong <me@alexdong.com>
License: MIT
License-File: LICENSE
Requires-Python: >=3.12
Provides-Extra: dev
Requires-Dist: pytest>=8.0; extra == 'dev'
